<bbgame source="STAT CREW Basketball" version="1.1.2" generated="4/19/2018">
  <venue gameid="GAME01"
           visid="COR" visname="Cornell"
           homeid="MASON" homename="George Mason"
           date="11/14/2014" location="Fairfax, Va. (Patriot Center)"
           time="7:30 pm" attend="6007" schednote=""
           leaguegame="N" neutralgame="N" postseason="N">
    <officials text="Kevin Ferguson, Edwin Young III, Damon Williams"></officials>
    <rules prds="2" minutes="20" minutesot="5" fouls="5" qh="H"></rules>
  </venue>
  <status complete="Y" period="2" clock="00:00" running="F"></status>
  <team vh="V" id="COR" name="Cornell" record="(1-0)">
    <linescore line="34,34" score="68">
      <lineprd prd="1" score="34"></lineprd>
      <lineprd prd="2" score="34"></lineprd>
    </linescore>
    <totals>
      <stats fgm="21" fga="47" fgm3="9" fga3="18" ftm="17" fta="28" tp="68" blk="3" stl="1" ast="9" min="200"
             oreb="6" dreb="40" treb="46" pf="21" tf="0" to="16" deadball="5,1"></stats>
      <special vh="V" pts_to="5" pts_ch2="4" pts_paint="18" pts_fastb="6" pts_bench="4" ties="2" leads="2"
               poss_count="88" poss_time="1205" score_count="20" score_time="421" large_lead="15" large_lead_t="2nd-01:30"></special>
    </totals>
    <player uni="00" code="00" name="Onuorah, David" checkname="ONUORAH,DAVID" gp="1" gs="1" pos="f" oncourt="Y">
      <stats fgm="2" fga="3" fgm3="0" fga3="0" ftm="2" fta="4" tp="6" blk="0" stl="0" ast="0" min="29"
             oreb="0" dreb="5" treb="5" pf="3" tf="0" to="1" dq="0"></stats>
    </player>
    <player uni="01" code="01" name="Smith, Darryl" checkname="SMITH,DARRYL" gp="1">
      <stats fgm="1" fga="1" fgm3="1" fga3="1" ftm="0" fta="0" tp="3" blk="0" stl="0" ast="0" min="17"
             oreb="0" dreb="2" treb="2" pf="0" tf="0" to="0" dq="0"></stats>
    </player>
    <player uni="04" code="04" name="LaMore, Dave" checkname="LAMORE,DAVE" gp="1">
      <stats fgm="0" fga="0" fgm3="0" fga3="0" ftm="0" fta="0" tp="0" blk="0" stl="0" ast="0" min="6"
             oreb="0" dreb="0" treb="0" pf="0" tf="0" to="0" dq="0"></stats>
    </player>
    <player uni="05" code="05" name="Hatter, Robert" checkname="HATTER,ROBERT" gp="1" gs="1" pos="g" oncourt="Y">
      <stats fgm="7" fga="10" fgm3="3" fga3="5" ftm="4" fta="5" tp="21" blk="0" stl="1" ast="0" min="28"
             oreb="1" dreb="4" treb="5" pf="4" tf="0" to="1" dq="0"></stats>
    </player>
    <player uni="11" code="11" name="Fleming, Desmond" checkname="FLEMING,DESMOND" gp="0"></player>
    <player uni="12" code="12" name="Abdur-Ra'oof, Jordan" checkname="ABDUR-RA'OOF,JORDAN" gp="1">
      <stats fgm="0" fga="2" fgm3="0" fga3="0" ftm="0" fta="0" tp="0" blk="0" stl="0" ast="0" min="4"
             oreb="0" dreb="0" treb="0" pf="1" tf="0" to="1" dq="0"></stats>
    </player>
    <player uni="13" code="13" name="Cherry, Devin" checkname="CHERRY,DEVIN" gp="1" gs="1" pos="g" oncourt="Y">
      <stats fgm="2" fga="6" fgm3="0" fga3="2" ftm="5" fta="10" tp="9" blk="0" stl="0" ast="7" min="39"
             oreb="0" dreb="10" treb="10" pf="3" tf="0" to="8" dq="0"></stats>
    </player>
    <player uni="15" code="15" name="Bunce, Braxston" checkname="BUNCE,BRAXSTON" gp="0"></player>
    <player uni="20" code="20" name="Bathurst, Wil" checkname="BATHURST,WIL" gp="1">
      <stats fgm="0" fga="1" fgm3="0" fga3="1" ftm="1" fta="2" tp="1" blk="0" stl="0" ast="0" min="4"
             oreb="0" dreb="1" treb="1" pf="2" tf="0" to="0" dq="0"></stats>
    </player>
    <player uni="21" code="21" name="Brown, Kyle" checkname="BROWN,KYLE" gp="0"></player>
    <player uni="22" code="22" name="Mischler, Robert" checkname="MISCHLER,ROBERT" gp="0"></player>
    <player uni="23" code="23" name="Cancer, Galal" checkname="CANCER,GALAL" gp="1" gs="1" pos="g" oncourt="Y">
      <stats fgm="2" fga="8" fgm3="1" fga3="3" ftm="2" fta="2" tp="7" blk="0" stl="0" ast="2" min="27"
             oreb="2" dreb="1" treb="3" pf="2" tf="0" to="1" dq="0"></stats>
    </player>
    <player uni="24" code="24" name="Smith, Pat" checkname="SMITH,PAT" gp="0"></player>
    <player uni="25" code="25" name="Fallas, JoJo" checkname="FALLAS,JOJO" gp="1">
      <stats fgm="0" fga="1" fgm3="0" fga3="0" ftm="0" fta="0" tp="0" blk="0" stl="0" ast="0" min="4"
             oreb="0" dreb="0" treb="0" pf="0" tf="0" to="0" dq="0"></stats>
    </player>
    <player uni="32" code="32" name="Miller, Shonn" checkname="MILLER,SHONN" gp="1" gs="1" pos="f" oncourt="Y">
      <stats fgm="7" fga="14" fgm3="4" fga3="6" ftm="3" fta="5" tp="21" blk="2" stl="0" ast="0" min="31"
             oreb="0" dreb="13" treb="13" pf="4" tf="0" to="3" dq="0"></stats>
    </player>
    <player uni="35" code="35" name="Tomic, Ned" checkname="TOMIC,NED" gp="1">
      <stats fgm="0" fga="0" fgm3="0" fga3="0" ftm="0" fta="0" tp="0" blk="0" stl="0" ast="0" min="2"
             oreb="0" dreb="0" treb="0" pf="0" tf="0" to="0" dq="0"></stats>
    </player>
    <player uni="50" code="50" name="Giddens, Deion" checkname="GIDDENS,DEION" gp="1">
      <stats fgm="0" fga="1" fgm3="0" fga3="0" ftm="0" fta="0" tp="0" blk="1" stl="0" ast="0" min="9"
             oreb="1" dreb="2" treb="3" pf="2" tf="0" to="1" dq="0"></stats>
    </player>
    <player uni="TM" code="TM" name="TEAM" checkname="TEAM" gp="1">
      <stats oreb="2" dreb="2" treb="4" pf="0" tf="0" to="0" dq="0"></stats>
    </player>
  </team>
  <team vh="H" id="MASON" name="George Mason" record="(0-1)">
    <linescore line="31,29" score="60">
      <lineprd prd="1" score="31"></lineprd>
      <lineprd prd="2" score="29"></lineprd>
    </linescore>
    <totals>
      <stats fgm="21" fga="68" fgm3="7" fga3="27" ftm="11" fta="21" tp="60" blk="4" stl="5" ast="11" min="200"
             oreb="13" dreb="25" treb="38" pf="24" tf="0" to="5" deadball="3,1"></stats>
      <special vh="H" pts_to="16" pts_ch2="7" pts_paint="18" pts_fastb="0" pts_bench="17" ties="2" leads="2"
               poss_count="88" poss_time="1190" score_count="22" score_time="382" large_lead="3" large_lead_t="1st-02:04"></special>
    </totals>
    <player uni="01" code="01" name="GRAY, Vaughn" checkname="GRAY,VAUGHN" gp="1">
      <stats fgm="1" fga="6" fgm3="1" fga3="5" ftm="0" fta="0" tp="3" blk="0" stl="1" ast="0" min="14"
             oreb="0" dreb="3" treb="3" pf="1" tf="0" to="0" dq="0"></stats>
    </player>
    <player uni="03" code="03" name="HOLLOWAY, Patrick" checkname="HOLLOWAY,PATRICK" gp="1" gs="1" pos="g" oncourt="Y">
      <stats fgm="7" fga="18" fgm3="4" fga3="11" ftm="4" fta="6" tp="22" blk="0" stl="0" ast="0" min="31"
             oreb="0" dreb="1" treb="1" pf="5" tf="0" to="2" dq="1"></stats>
    </player>
    <player uni="04" code="04" name="COPES, Erik" checkname="COPES,ERIK" gp="1">
      <stats fgm="0" fga="1" fgm3="0" fga3="0" ftm="1" fta="2" tp="1" blk="2" stl="0" ast="0" min="13"
             oreb="1" dreb="1" treb="2" pf="2" tf="0" to="0" dq="0"></stats>
    </player>
    <player uni="05" code="05" name="LOCKETT, Eric" checkname="LOCKETT,ERIC" gp="1">
      <stats fgm="0" fga="0" fgm3="0" fga3="0" ftm="0" fta="0" tp="0" blk="1" stl="0" ast="0" min="6"
             oreb="0" dreb="0" treb="0" pf="0" tf="0" to="0" dq="0"></stats>
    </player>
    <player uni="10" code="10" name="GUJANICIC, Marko" checkname="GUJANICIC,MARKO" gp="1" gs="1" pos="f">
      <stats fgm="0" fga="3" fgm3="0" fga3="1" ftm="0" fta="0" tp="0" blk="0" stl="0" ast="2" min="9"
             oreb="0" dreb="1" treb="1" pf="1" tf="0" to="1" dq="0"></stats>
    </player>
    <player uni="12" code="12" name="TATE, Myles" checkname="TATE,MYLES" gp="0"></player>
    <player uni="13" code="13" name="EDWARDS, Corey" checkname="EDWARDS,COREY" gp="1">
      <stats fgm="1" fga="5" fgm3="1" fga3="2" ftm="0" fta="0" tp="3" blk="1" stl="0" ast="1" min="20"
             oreb="0" dreb="0" treb="0" pf="2" tf="0" to="0" dq="0"></stats>
    </player>
    <player uni="14" code="14" name="THOMPSON, Shevon" checkname="THOMPSON,SHEVON" gp="1" gs="1" pos="c" oncourt="Y">
      <stats fgm="1" fga="6" fgm3="0" fga3="0" ftm="1" fta="2" tp="3" blk="0" stl="0" ast="0" min="27"
             oreb="3" dreb="7" treb="10" pf="2" tf="0" to="0" dq="0"></stats>
    </player>
    <player uni="15" code="15" name="PORTER, Trey" checkname="PORTER,TREY" gp="0"></player>
    <player uni="22" code="22" name="MOORE, Marquise" checkname="MOORE,MARQUISE" gp="1" gs="1" pos="g" oncourt="Y">
      <stats fgm="2" fga="6" fgm3="0" fga3="1" ftm="4" fta="7" tp="8" blk="0" stl="1" ast="7" min="36"
             oreb="2" dreb="4" treb="6" pf="4" tf="0" to="1" dq="0"></stats>
    </player>
    <player uni="23" code="23" name="MAYIMBA, Therence" checkname="MAYIMBA,THERENCE" gp="0"></player>
    <player uni="25" code="25" name="ROYAL, Julian" checkname="ROYAL,JULIAN" gp="1">
      <stats fgm="2" fga="8" fgm3="0" fga3="4" ftm="1" fta="2" tp="5" blk="0" stl="0" ast="0" min="14"
             oreb="0" dreb="3" treb="3" pf="1" tf="0" to="0" dq="0"></stats>
    </player>
    <player uni="30" code="30" name="RUDY, Michael" checkname="RUDY,MICHAEL" gp="0"></player>
    <player uni="31" code="31" name="JENKINS, Jalen" checkname="JENKINS,JALEN" gp="1" gs="1" pos="f" oncourt="Y">
      <stats fgm="5" fga="9" fgm3="0" fga3="0" ftm="0" fta="2" tp="10" blk="0" stl="3" ast="0" min="22"
             oreb="2" dreb="2" treb="4" pf="4" tf="0" to="1" dq="0"></stats>
    </player>
    <player uni="44" code="44" name="JACKSON, Isaiah" checkname="JACKSON,ISAIAH" gp="1" oncourt="Y">
      <stats fgm="2" fga="6" fgm3="1" fga3="3" ftm="0" fta="0" tp="5" blk="0" stl="0" ast="1" min="8"
             oreb="1" dreb="2" treb="3" pf="2" tf="0" to="0" dq="0"></stats>
    </player>
    <player uni="TM" code="TM" name="TEAM" checkname="TEAM" gp="1">
      <stats oreb="4" dreb="1" treb="5" pf="0" tf="0" to="0" dq="0"></stats>
    </player>
  </team>
  <plays format="tokens">
    <period number="1" time="20:00">
      <special vh="V" pts_to="3" pts_ch2="2" pts_paint="4" pts_fastb="2" pts_bench="1" ties="2" leads="2"
               poss_count="42" poss_time="544" score_count="10" score_time="149" large_lead="15" large_lead_t="2nd-01:30"></special>
      <special vh="H" pts_to="9" pts_ch2="2" pts_paint="12" pts_fastb="0" pts_bench="10" ties="2" leads="2"
               poss_count="43" poss_time="653" score_count="11" score_time="227" large_lead="3" large_lead_t="1st-02:04"></special>
      <summary vh="V" fgm="10" fga="22" fgm3="6" fga3="8" ftm="8" fta="14" blk="2" stl="1" ast="6"
               oreb="2" dreb="19" treb="21" pf="10" tf="0" to="8"></summary>
      <summary vh="H" fgm="11" fga="33" fgm3="4" fga3="11" ftm="5" fta="7" blk="1" stl="1" ast="7"
               oreb="5" dreb="14" treb="19" pf="11" tf="0" to="3"></summary>
      <play vh="H" time="19:40" uni="03" team="MASON" checkname="HOLLOWAY,PATRICK" action="TURNOVER"></play>
      <play vh="V" time="19:27" uni="32" team="COR" checkname="MILLER,SHONN" action="MISS" type="JUMPER"></play>
      <play vh="H" time="19:27" uni="14" team="MASON" checkname="THOMPSON,SHEVON" action="REBOUND" type="DEF"></play>
      <play vh="H" time="19:11" uni="10" team="MASON" checkname="GUJANICIC,MARKO" action="MISS" type="JUMPER"></play>
      <play vh="V" time="19:11" uni="00" team="COR" checkname="ONUORAH,DAVID" action="REBOUND" type="DEF"></play>
      <play vh="H" time="19:10" uni="14" team="MASON" checkname="THOMPSON,SHEVON" action="FOUL"></play>
      <play vh="V" time="18:56" uni="13" team="COR" checkname="CHERRY,DEVIN" action="TURNOVER"></play>
      <play vh="H" time="18:54" uni="31" team="MASON" checkname="JENKINS,JALEN" action="STEAL"></play>
      <play vh="H" time="18:47" uni="22" team="MASON" checkname="MOORE,MARQUISE" action="MISS" type="JUMPER"></play>
      <play vh="V" time="18:47" uni="05" team="COR" checkname="HATTER,ROBERT" action="REBOUND" type="DEF"></play>
      <play vh="H" time="18:44" uni="31" team="MASON" checkname="JENKINS,JALEN" action="FOUL"></play>
      <play vh="V" time="18:23" uni="05" team="COR" checkname="HATTER,ROBERT" action="GOOD" type="JUMPER" paint="Y" vscore="2" hscore="0"></play>
      <play vh="H" time="18:09" uni="03" team="MASON" checkname="HOLLOWAY,PATRICK" action="MISS" type="3PTR"></play>
      <play vh="V" time="18:09" uni="32" team="COR" checkname="MILLER,SHONN" action="REBOUND" type="DEF"></play>
      <play vh="V" time="17:58" uni="32" team="COR" checkname="MILLER,SHONN" action="TURNOVER"></play>
      <play vh="H" time="17:30" uni="31" team="MASON" checkname="JENKINS,JALEN" action="GOOD" type="JUMPER" paint="Y" vscore="2" hscore="2"></play>
      <play vh="V" time="17:20" uni="32" team="COR" checkname="MILLER,SHONN" action="GOOD" type="3PTR" vscore="5" hscore="2"></play>
      <play vh="V" time="17:20" uni="13" team="COR" checkname="CHERRY,DEVIN" action="ASSIST"></play>
      <play vh="V" time="17:08" uni="32" team="COR" checkname="MILLER,SHONN" action="FOUL"></play>
      <play vh="H" time="16:58" uni="10" team="MASON" checkname="GUJANICIC,MARKO" action="TURNOVER"></play>
      <play vh="V" time="16:57" uni="05" team="COR" checkname="HATTER,ROBERT" action="STEAL"></play>
      <play vh="V" time="16:52" uni="23" team="COR" checkname="CANCER,GALAL" action="GOOD" type="3PTR" vscore="8" hscore="2"></play>
      <play vh="V" time="16:52" uni="13" team="COR" checkname="CHERRY,DEVIN" action="ASSIST"></play>
      <play vh="V" time="16:35" uni="05" team="COR" checkname="HATTER,ROBERT" action="FOUL"></play>
      <play vh="H" time="16:35" uni="22" team="MASON" checkname="MOORE,MARQUISE" action="GOOD" type="FT" vscore="8" hscore="3"></play>
      <play vh="H" time="16:35" uni="22" team="MASON" checkname="MOORE,MARQUISE" action="GOOD" type="FT" vscore="8" hscore="4"></play>
      <play vh="V" time="16:35" uni="12" team="COR" checkname="ABDUR-RA'OOF,JORDAN" action="SUB" type="IN"></play>
      <play vh="V" time="16:35" uni="32" team="COR" checkname="MILLER,SHONN" action="SUB" type="OUT"></play>
      <play vh="H" time="16:35" uni="01" team="MASON" checkname="GRAY,VAUGHN" action="SUB" type="IN"></play>
      <play vh="H" time="16:35" uni="10" team="MASON" checkname="GUJANICIC,MARKO" action="SUB" type="OUT"></play>
      <play vh="V" time="16:20" uni="12" team="COR" checkname="ABDUR-RA'OOF,JORDAN" action="FOUL"></play>
      <play vh="V" time="16:20" uni="12" team="COR" checkname="ABDUR-RA'OOF,JORDAN" action="TURNOVER"></play>
      <play vh="H" time="16:02" uni="31" team="MASON" checkname="JENKINS,JALEN" action="GOOD" type="JUMPER" paint="Y" vscore="8" hscore="6"></play>
      <play vh="V" time="15:47" uni="12" team="COR" checkname="ABDUR-RA'OOF,JORDAN" action="MISS" type="JUMPER"></play>
      <play vh="H" time="15:47" uni="01" team="MASON" checkname="GRAY,VAUGHN" action="REBOUND" type="DEF"></play>
      <play vh="H" time="15:27" uni="31" team="MASON" checkname="JENKINS,JALEN" action="GOOD" type="DUNK" paint="Y" vscore="8" hscore="8"></play>
      <play vh="H" time="15:27" uni="22" team="MASON" checkname="MOORE,MARQUISE" action="ASSIST"></play>
      <play vh="V" time="15:09" uni="05" team="COR" checkname="HATTER,ROBERT" action="GOOD" type="3PTR" vscore="11" hscore="8"></play>
      <play vh="V" time="15:09" uni="13" team="COR" checkname="CHERRY,DEVIN" action="ASSIST"></play>
      <play vh="H" time="14:44" uni="14" team="MASON" checkname="THOMPSON,SHEVON" action="MISS" type="JUMPER"></play>
      <play vh="V" time="14:44" uni="13" team="COR" checkname="CHERRY,DEVIN" action="REBOUND" type="DEF"></play>
      <play vh="V" time="14:36" uni="23" team="COR" checkname="CANCER,GALAL" action="GOOD" type="JUMPER" fastb="Y" vscore="13" hscore="8"></play>
      <play vh="H" time="14:20" uni="14" team="MASON" checkname="THOMPSON,SHEVON" action="GOOD" type="DUNK" paint="Y" vscore="13" hscore="10"></play>
      <play vh="H" time="14:20" uni="22" team="MASON" checkname="MOORE,MARQUISE" action="ASSIST"></play>
      <play vh="V" time="14:07" uni="05" team="COR" checkname="HATTER,ROBERT" action="GOOD" type="3PTR" vscore="16" hscore="10"></play>
      <play vh="V" time="14:07" uni="23" team="COR" checkname="CANCER,GALAL" action="ASSIST"></play>
      <play vh="H" time="13:40" uni="31" team="MASON" checkname="JENKINS,JALEN" action="MISS" type="JUMPER"></play>
      <play vh="V" time="13:40" uni="13" team="COR" checkname="CHERRY,DEVIN" action="REBOUND" type="DEF"></play>
      <play vh="V" time="13:29" uni="12" team="COR" checkname="ABDUR-RA'OOF,JORDAN" action="MISS" type="JUMPER"></play>
      <play vh="H" time="13:29" uni="14" team="MASON" checkname="THOMPSON,SHEVON" action="REBOUND" type="DEF"></play>
      <play vh="H" time="13:11" uni="22" team="MASON" checkname="MOORE,MARQUISE" action="MISS" type="JUMPER"></play>
      <play vh="V" time="13:11" uni="13" team="COR" checkname="CHERRY,DEVIN" action="REBOUND" type="DEF"></play>
      <play vh="V" time="13:01" uni="23" team="COR" checkname="CANCER,GALAL" action="MISS" type="LAYUP"></play>
      <play vh="H" time="13:01" uni="14" team="MASON" checkname="THOMPSON,SHEVON" action="REBOUND" type="DEF"></play>
      <play vh="V" time="12:59" uni="23" team="COR" checkname="CANCER,GALAL" action="FOUL"></play>
      <play vh="H" time="12:59" uni="TM" team="MASON" checkname="TEAM" action="TIMEOUT" type="MEDIA"></play>
      <play vh="V" time="12:59" uni="25" team="COR" checkname="FALLAS,JOJO" action="SUB" type="IN"></play>
      <play vh="V" time="12:59" uni="32" team="COR" checkname="MILLER,SHONN" action="SUB" type="IN"></play>
      <play vh="V" time="12:59" uni="50" team="COR" checkname="GIDDENS,DEION" action="SUB" type="IN"></play>
      <play vh="V" time="12:59" uni="00" team="COR" checkname="ONUORAH,DAVID" action="SUB" type="OUT"></play>
      <play vh="V" time="12:59" uni="05" team="COR" checkname="HATTER,ROBERT" action="SUB" type="OUT"></play>
      <play vh="V" time="12:59" uni="12" team="COR" checkname="ABDUR-RA'OOF,JORDAN" action="SUB" type="OUT"></play>
      <play vh="H" time="12:59" uni="04" team="MASON" checkname="COPES,ERIK" action="SUB" type="IN"></play>
      <play vh="H" time="12:59" uni="25" team="MASON" checkname="ROYAL,JULIAN" action="SUB" type="IN"></play>
      <play vh="H" time="12:59" uni="14" team="MASON" checkname="THOMPSON,SHEVON" action="SUB" type="OUT"></play>
      <play vh="H" time="12:59" uni="31" team="MASON" checkname="JENKINS,JALEN" action="SUB" type="OUT"></play>
      <play vh="H" time="12:50" uni="01" team="MASON" checkname="GRAY,VAUGHN" action="MISS" type="3PTR"></play>
      <play vh="H" time="12:50" uni="TM" team="MASON" checkname="TEAM" action="REBOUND" type="OFF"></play>
      <play vh="H" time="12:47" uni="03" team="MASON" checkname="HOLLOWAY,PATRICK" action="MISS" type="3PTR"></play>
      <play vh="V" time="12:47" uni="32" team="COR" checkname="MILLER,SHONN" action="REBOUND" type="DEF"></play>
      <play vh="V" time="12:34" uni="23" team="COR" checkname="CANCER,GALAL" action="MISS" type="JUMPER"></play>
      <play vh="H" time="12:34" uni="25" team="MASON" checkname="ROYAL,JULIAN" action="REBOUND" type="DEF"></play>
      <play vh="H" time="12:26" uni="25" team="MASON" checkname="ROYAL,JULIAN" action="MISS" type="JUMPER"></play>
      <play vh="V" time="12:26" uni="50" team="COR" checkname="GIDDENS,DEION" action="BLOCK"></play>
      <play vh="V" time="12:24" uni="50" team="COR" checkname="GIDDENS,DEION" action="REBOUND" type="DEF"></play>
      <play vh="V" time="12:10" uni="32" team="COR" checkname="MILLER,SHONN" action="MISS" type="3PTR"></play>
      <play vh="H" time="12:10" uni="01" team="MASON" checkname="GRAY,VAUGHN" action="REBOUND" type="DEF"></play>
      <play vh="H" time="12:03" uni="01" team="MASON" checkname="GRAY,VAUGHN" action="MISS" type="JUMPER"></play>
      <play vh="V" time="12:03" uni="13" team="COR" checkname="CHERRY,DEVIN" action="REBOUND" type="DEF"></play>
      <play vh="V" time="11:57" uni="50" team="COR" checkname="GIDDENS,DEION" action="FOUL"></play>
      <play vh="V" time="11:57" uni="50" team="COR" checkname="GIDDENS,DEION" action="TURNOVER"></play>
      <play vh="H" time="11:57" uni="TM" team="MASON" checkname="TEAM" action="TIMEOUT" type="MEDIA"></play>
      <play vh="V" time="11:57" uni="01" team="COR" checkname="SMITH,DARRYL" action="SUB" type="IN"></play>
      <play vh="V" time="11:57" uni="23" team="COR" checkname="CANCER,GALAL" action="SUB" type="OUT"></play>
      <play vh="H" time="11:43" uni="25" team="MASON" checkname="ROYAL,JULIAN" action="MISS" type="3PTR"></play>
      <play vh="V" time="11:43" uni="01" team="COR" checkname="SMITH,DARRYL" action="REBOUND" type="DEF"></play>
      <play vh="V" time="11:18" uni="13" team="COR" checkname="CHERRY,DEVIN" action="TURNOVER"></play>
      <play vh="V" time="11:18" uni="05" team="COR" checkname="HATTER,ROBERT" action="SUB" type="IN"></play>
      <play vh="V" time="11:18" uni="25" team="COR" checkname="FALLAS,JOJO" action="SUB" type="OUT"></play>
      <play vh="H" time="11:00" uni="03" team="MASON" checkname="HOLLOWAY,PATRICK" action="MISS" type="LAYUP"></play>
      <play vh="V" time="11:00" uni="32" team="COR" checkname="MILLER,SHONN" action="BLOCK"></play>
      <play vh="V" time="10:58" uni="32" team="COR" checkname="MILLER,SHONN" action="REBOUND" type="DEF"></play>
      <play vh="V" time="10:49" uni="32" team="COR" checkname="MILLER,SHONN" action="MISS" type="JUMPER"></play>
      <play vh="H" time="10:49" uni="01" team="MASON" checkname="GRAY,VAUGHN" action="REBOUND" type="DEF"></play>
      <play vh="H" time="10:34" uni="01" team="MASON" checkname="GRAY,VAUGHN" action="MISS" type="3PTR"></play>
      <play vh="V" time="10:34" uni="32" team="COR" checkname="MILLER,SHONN" action="REBOUND" type="DEF"></play>
      <play vh="H" time="10:28" uni="03" team="MASON" checkname="HOLLOWAY,PATRICK" action="FOUL"></play>
      <play vh="V" time="10:28" uni="23" team="COR" checkname="CANCER,GALAL" action="SUB" type="IN"></play>
      <play vh="V" time="10:28" uni="13" team="COR" checkname="CHERRY,DEVIN" action="SUB" type="OUT"></play>
      <play vh="H" time="10:28" uni="13" team="MASON" checkname="EDWARDS,COREY" action="SUB" type="IN"></play>
      <play vh="H" time="10:28" uni="22" team="MASON" checkname="MOORE,MARQUISE" action="SUB" type="OUT"></play>
      <play vh="H" time="10:19" uni="31" team="MASON" checkname="JENKINS,JALEN" action="SUB" type="IN"></play>
      <play vh="H" time="10:19" uni="25" team="MASON" checkname="ROYAL,JULIAN" action="SUB" type="OUT"></play>
      <play vh="V" time="10:11" uni="23" team="COR" checkname="CANCER,GALAL" action="MISS" type="LAYUP"></play>
      <play vh="V" time="10:11" uni="23" team="COR" checkname="CANCER,GALAL" action="REBOUND" type="OFF"></play>
      <play vh="H" time="10:08" uni="31" team="MASON" checkname="JENKINS,JALEN" action="FOUL"></play>
      <play vh="V" time="10:08" uni="23" team="COR" checkname="CANCER,GALAL" action="GOOD" type="FT" vscore="17" hscore="10"></play>
      <play vh="V" time="10:08" uni="23" team="COR" checkname="CANCER,GALAL" action="GOOD" type="FT" vscore="18" hscore="10"></play>
      <play vh="H" time="10:08" uni="25" team="MASON" checkname="ROYAL,JULIAN" action="SUB" type="IN"></play>
      <play vh="H" time="10:08" uni="31" team="MASON" checkname="JENKINS,JALEN" action="SUB" type="OUT"></play>
      <play vh="H" time="09:50" uni="01" team="MASON" checkname="GRAY,VAUGHN" action="GOOD" type="3PTR" vscore="18" hscore="13"></play>
      <play vh="H" time="09:50" uni="13" team="MASON" checkname="EDWARDS,COREY" action="ASSIST"></play>
      <play vh="H" time="09:35" uni="04" team="MASON" checkname="COPES,ERIK" action="FOUL"></play>
      <play vh="V" time="09:35" uni="13" team="COR" checkname="CHERRY,DEVIN" action="SUB" type="IN"></play>
      <play vh="V" time="09:35" uni="01" team="COR" checkname="SMITH,DARRYL" action="SUB" type="OUT"></play>
      <play vh="H" time="09:23" uni="03" team="MASON" checkname="HOLLOWAY,PATRICK" action="FOUL"></play>
      <play vh="V" time="09:23" uni="05" team="COR" checkname="HATTER,ROBERT" action="GOOD" type="FT" vscore="19" hscore="13"></play>
      <play vh="V" time="09:23" uni="05" team="COR" checkname="HATTER,ROBERT" action="GOOD" type="FT" vscore="20" hscore="13"></play>
      <play vh="V" time="09:23" uni="05" team="COR" checkname="HATTER,ROBERT" action="MISS" type="FT"></play>
      <play vh="H" time="09:23" uni="22" team="MASON" checkname="MOORE,MARQUISE" action="REBOUND" type="DEF"></play>
      <play vh="H" time="09:23" uni="22" team="MASON" checkname="MOORE,MARQUISE" action="SUB" type="IN"></play>
      <play vh="H" time="09:23" uni="03" team="MASON" checkname="HOLLOWAY,PATRICK" action="SUB" type="OUT"></play>
      <play vh="H" time="08:57" uni="25" team="MASON" checkname="ROYAL,JULIAN" action="MISS" type="3PTR"></play>
      <play vh="V" time="08:57" uni="05" team="COR" checkname="HATTER,ROBERT" action="REBOUND" type="DEF"></play>
      <play vh="H" time="08:39" uni="04" team="MASON" checkname="COPES,ERIK" action="FOUL"></play>
      <play vh="V" time="08:39" uni="32" team="COR" checkname="MILLER,SHONN" action="MISS" type="FT"></play>
      <play vh="V" time="08:39" uni="TM" team="COR" checkname="TEAM" action="REBOUND" type="DEADB"></play>
      <play vh="V" time="08:39" uni="32" team="COR" checkname="MILLER,SHONN" action="MISS" type="FT"></play>
      <play vh="V" time="08:39" uni="50" team="COR" checkname="GIDDENS,DEION" action="REBOUND" type="OFF"></play>
      <play vh="H" time="08:39" uni="14" team="MASON" checkname="THOMPSON,SHEVON" action="SUB" type="IN"></play>
      <play vh="H" time="08:39" uni="04" team="MASON" checkname="COPES,ERIK" action="SUB" type="OUT"></play>
      <play vh="V" time="08:22" uni="32" team="COR" checkname="MILLER,SHONN" action="MISS" type="JUMPER"></play>
      <play vh="H" time="08:22" uni="22" team="MASON" checkname="MOORE,MARQUISE" action="REBOUND" type="DEF"></play>
      <play vh="H" time="08:11" uni="13" team="MASON" checkname="EDWARDS,COREY" action="MISS" type="JUMPER"></play>
      <play vh="H" time="08:11" uni="14" team="MASON" checkname="THOMPSON,SHEVON" action="REBOUND" type="OFF"></play>
      <play vh="H" time="08:07" uni="25" team="MASON" checkname="ROYAL,JULIAN" action="MISS" type="JUMPER"></play>
      <play vh="H" time="08:07" uni="14" team="MASON" checkname="THOMPSON,SHEVON" action="REBOUND" type="OFF"></play>
      <play vh="V" time="08:05" uni="05" team="COR" checkname="HATTER,ROBERT" action="FOUL"></play>
      <play vh="V" time="08:05" uni="00" team="COR" checkname="ONUORAH,DAVID" action="SUB" type="IN"></play>
      <play vh="V" time="08:05" uni="25" team="COR" checkname="FALLAS,JOJO" action="SUB" type="IN"></play>
      <play vh="V" time="08:05" uni="35" team="COR" checkname="TOMIC,NED" action="SUB" type="IN"></play>
      <play vh="V" time="08:05" uni="05" team="COR" checkname="HATTER,ROBERT" action="SUB" type="OUT"></play>
      <play vh="V" time="08:05" uni="32" team="COR" checkname="MILLER,SHONN" action="SUB" type="OUT"></play>
      <play vh="V" time="08:05" uni="50" team="COR" checkname="GIDDENS,DEION" action="SUB" type="OUT"></play>
      <play vh="H" time="07:54" uni="14" team="MASON" checkname="THOMPSON,SHEVON" action="MISS" type="JUMPER"></play>
      <play vh="H" time="07:54" uni="22" team="MASON" checkname="MOORE,MARQUISE" action="REBOUND" type="OFF"></play>
      <play vh="H" time="07:52" uni="22" team="MASON" checkname="MOORE,MARQUISE" action="GOOD" type="JUMPER" paint="Y" vscore="20" hscore="15"></play>
      <play vh="V" time="07:52" uni="23" team="COR" checkname="CANCER,GALAL" action="FOUL"></play>
      <play vh="H" time="07:52" uni="TM" team="MASON" checkname="TEAM" action="TIMEOUT" type="media"></play>
      <play vh="H" time="07:52" uni="22" team="MASON" checkname="MOORE,MARQUISE" action="MISS" type="FT"></play>
      <play vh="H" time="07:52" uni="TM" team="MASON" checkname="TEAM" action="REBOUND" type="OFF"></play>
      <play vh="H" time="07:37" uni="05" team="MASON" checkname="LOCKETT,ERIC" action="SUB" type="IN"></play>
      <play vh="H" time="07:37" uni="01" team="MASON" checkname="GRAY,VAUGHN" action="SUB" type="OUT"></play>
      <play vh="H" time="07:23" uni="25" team="MASON" checkname="ROYAL,JULIAN" action="MISS" type="3PTR"></play>
      <play vh="V" time="07:23" uni="13" team="COR" checkname="CHERRY,DEVIN" action="REBOUND" type="DEF"></play>
      <play vh="V" time="07:14" uni="25" team="COR" checkname="FALLAS,JOJO" action="MISS" type="JUMPER"></play>
      <play vh="H" time="07:14" uni="05" team="MASON" checkname="LOCKETT,ERIC" action="BLOCK"></play>
      <play vh="H" time="07:12" uni="TM" team="MASON" checkname="TEAM" action="REBOUND" type="DEF"></play>
      <play vh="H" time="07:11" uni="23" team="MASON" checkname="MAYIMBA,THERENCE" action="SUB" type="IN"></play>
      <play vh="H" time="07:11" uni="03" team="MASON" checkname="HOLLOWAY,PATRICK" action="SUB" type="IN"></play>
      <play vh="H" time="07:11" uni="10" team="MASON" checkname="GUJANICIC,MARKO" action="SUB" type="IN"></play>
      <play vh="H" time="07:11" uni="05" team="MASON" checkname="LOCKETT,ERIC" action="SUB" type="OUT"></play>
      <play vh="H" time="07:11" uni="13" team="MASON" checkname="EDWARDS,COREY" action="SUB" type="OUT"></play>
      <play vh="H" time="07:11" uni="25" team="MASON" checkname="ROYAL,JULIAN" action="SUB" type="OUT"></play>
      <play vh="H" time="06:55" uni="10" team="MASON" checkname="GUJANICIC,MARKO" action="MISS" type="JUMPER"></play>
      <play vh="V" time="06:55" uni="01" team="COR" checkname="SMITH,DARRYL" action="REBOUND" type="DEF"></play>
      <play vh="V" time="06:33" uni="20" team="COR" checkname="BATHURST,WIL" action="MISS" type="3PTR"></play>
      <play vh="H" time="06:33" uni="14" team="MASON" checkname="THOMPSON,SHEVON" action="REBOUND" type="DEF"></play>
      <play vh="H" time="06:25" uni="22" team="MASON" checkname="MOORE,MARQUISE" action="TURNOVER"></play>
      <play vh="V" time="06:25" uni="32" team="COR" checkname="MILLER,SHONN" action="SUB" type="IN"></play>
      <play vh="V" time="06:25" uni="35" team="COR" checkname="TOMIC,NED" action="SUB" type="OUT"></play>
      <play vh="V" time="06:17" uni="00" team="COR" checkname="ONUORAH,DAVID" action="FOUL"></play>
      <play vh="V" time="06:17" uni="00" team="COR" checkname="ONUORAH,DAVID" action="TURNOVER"></play>
      <play vh="H" time="06:03" uni="03" team="MASON" checkname="HOLLOWAY,PATRICK" action="GOOD" type="3PTR" vscore="20" hscore="18"></play>
      <play vh="H" time="06:03" uni="10" team="MASON" checkname="GUJANICIC,MARKO" action="ASSIST"></play>
      <play vh="V" time="05:44" uni="00" team="COR" checkname="ONUORAH,DAVID" action="MISS" type="JUMPER"></play>
      <play vh="H" time="05:44" uni="10" team="MASON" checkname="GUJANICIC,MARKO" action="REBOUND" type="DEF"></play>
      <play vh="H" time="05:37" uni="03" team="MASON" checkname="HOLLOWAY,PATRICK" action="GOOD" type="3PTR" vscore="20" hscore="21"></play>
      <play vh="H" time="05:37" uni="10" team="MASON" checkname="GUJANICIC,MARKO" action="ASSIST"></play>
      <play vh="V" time="05:29" uni="TM" team="COR" checkname="TEAM" action="TIMEOUT" type="30SEC"></play>
      <play vh="V" time="05:29" uni="01" team="COR" checkname="SMITH,DARRYL" action="SUB" type="IN"></play>
      <play vh="V" time="05:29" uni="20" team="COR" checkname="BATHURST,WIL" action="SUB" type="IN"></play>
      <play vh="V" time="05:29" uni="23" team="COR" checkname="CANCER,GALAL" action="SUB" type="OUT"></play>
      <play vh="V" time="05:29" uni="25" team="COR" checkname="FALLAS,JOJO" action="SUB" type="OUT"></play>
      <play vh="H" time="05:20" uni="25" team="MASON" checkname="ROYAL,JULIAN" action="FOUL"></play>
      <play vh="V" time="05:20" uni="00" team="COR" checkname="ONUORAH,DAVID" action="GOOD" type="FT" vscore="21" hscore="21"></play>
      <play vh="V" time="05:20" uni="00" team="COR" checkname="ONUORAH,DAVID" action="MISS" type="FT"></play>
      <play vh="H" time="05:20" uni="22" team="MASON" checkname="MOORE,MARQUISE" action="REBOUND" type="DEF"></play>
      <play vh="V" time="05:01" uni="20" team="COR" checkname="BATHURST,WIL" action="FOUL"></play>
      <play vh="H" time="05:01" uni="03" team="MASON" checkname="HOLLOWAY,PATRICK" action="GOOD" type="FT" vscore="21" hscore="22"></play>
      <play vh="H" time="05:01" uni="03" team="MASON" checkname="HOLLOWAY,PATRICK" action="GOOD" type="FT" vscore="21" hscore="23"></play>
      <play vh="H" time="05:01" uni="05" team="MASON" checkname="LOCKETT,ERIC" action="SUB" type="IN"></play>
      <play vh="H" time="05:01" uni="23" team="MASON" checkname="MAYIMBA,THERENCE" action="SUB" type="OUT"></play>
      <play vh="V" time="04:43" uni="32" team="COR" checkname="MILLER,SHONN" action="TURNOVER"></play>
      <play vh="H" time="04:22" uni="03" team="MASON" checkname="HOLLOWAY,PATRICK" action="MISS" type="LAYUP"></play>
      <play vh="V" time="04:22" uni="TM" team="COR" checkname="TEAM" action="REBOUND" type="DEF"></play>
      <play vh="H" time="03:58" uni="22" team="MASON" checkname="MOORE,MARQUISE" action="FOUL"></play>
      <play vh="V" time="03:58" uni="20" team="COR" checkname="BATHURST,WIL" action="MISS" type="FT"></play>
      <play vh="V" time="03:58" uni="TM" team="COR" checkname="TEAM" action="REBOUND" type="DEADB"></play>
      <play vh="V" time="03:58" uni="20" team="COR" checkname="BATHURST,WIL" action="GOOD" type="FT" vscore="22" hscore="23"></play>
      <play vh="V" time="03:50" uni="20" team="COR" checkname="BATHURST,WIL" action="FOUL"></play>
      <play vh="H" time="03:50" uni="TM" team="MASON" checkname="TEAM" action="TIMEOUT" type="MEDIA"></play>
      <play vh="H" time="03:50" uni="22" team="MASON" checkname="MOORE,MARQUISE" action="GOOD" type="FT" vscore="22" hscore="24"></play>
      <play vh="H" time="03:50" uni="22" team="MASON" checkname="MOORE,MARQUISE" action="MISS" type="FT"></play>
      <play vh="V" time="03:50" uni="20" team="COR" checkname="BATHURST,WIL" action="REBOUND" type="DEF"></play>
      <play vh="H" time="03:50" uni="13" team="MASON" checkname="EDWARDS,COREY" action="SUB" type="IN"></play>
      <play vh="H" time="03:50" uni="03" team="MASON" checkname="HOLLOWAY,PATRICK" action="SUB" type="OUT"></play>
      <play vh="H" time="03:33" uni="13" team="MASON" checkname="EDWARDS,COREY" action="FOUL"></play>
      <play vh="V" time="03:33" uni="00" team="COR" checkname="ONUORAH,DAVID" action="GOOD" type="FT" vscore="23" hscore="24"></play>
      <play vh="V" time="03:33" uni="00" team="COR" checkname="ONUORAH,DAVID" action="MISS" type="FT"></play>
      <play vh="H" time="03:33" uni="25" team="MASON" checkname="ROYAL,JULIAN" action="REBOUND" type="DEF"></play>
      <play vh="V" time="03:33" uni="23" team="COR" checkname="CANCER,GALAL" action="SUB" type="IN"></play>
      <play vh="V" time="03:33" uni="05" team="COR" checkname="HATTER,ROBERT" action="SUB" type="IN"></play>
      <play vh="V" time="03:33" uni="01" team="COR" checkname="SMITH,DARRYL" action="SUB" type="OUT"></play>
      <play vh="V" time="03:33" uni="20" team="COR" checkname="BATHURST,WIL" action="SUB" type="OUT"></play>
      <play vh="H" time="03:33" uni="25" team="MASON" checkname="ROYAL,JULIAN" action="SUB" type="IN"></play>
      <play vh="H" time="03:33" uni="10" team="MASON" checkname="GUJANICIC,MARKO" action="SUB" type="OUT"></play>
      <play vh="H" time="03:10" uni="22" team="MASON" checkname="MOORE,MARQUISE" action="MISS" type="JUMPER"></play>
      <play vh="V" time="03:10" uni="13" team="COR" checkname="CHERRY,DEVIN" action="REBOUND" type="DEF"></play>
      <play vh="V" time="03:02" uni="32" team="COR" checkname="MILLER,SHONN" action="GOOD" type="3PTR" vscore="26" hscore="24"></play>
      <play vh="V" time="03:02" uni="13" team="COR" checkname="CHERRY,DEVIN" action="ASSIST"></play>
      <play vh="H" time="02:40" uni="13" team="MASON" checkname="EDWARDS,COREY" action="GOOD" type="3PTR" vscore="26" hscore="27"></play>
      <play vh="H" time="02:40" uni="22" team="MASON" checkname="MOORE,MARQUISE" action="ASSIST"></play>
      <play vh="V" time="02:26" uni="23" team="COR" checkname="CANCER,GALAL" action="TURNOVER"></play>
      <play vh="V" time="02:26" uni="20" team="COR" checkname="BATHURST,WIL" action="SUB" type="IN"></play>
      <play vh="V" time="02:26" uni="01" team="COR" checkname="SMITH,DARRYL" action="SUB" type="IN"></play>
      <play vh="V" time="02:26" uni="23" team="COR" checkname="CANCER,GALAL" action="SUB" type="OUT"></play>
      <play vh="V" time="02:26" uni="05" team="COR" checkname="HATTER,ROBERT" action="SUB" type="OUT"></play>
      <play vh="H" time="02:26" uni="01" team="MASON" checkname="GRAY,VAUGHN" action="SUB" type="IN"></play>
      <play vh="H" time="02:26" uni="05" team="MASON" checkname="LOCKETT,ERIC" action="SUB" type="OUT"></play>
      <play vh="H" time="02:04" uni="25" team="MASON" checkname="ROYAL,JULIAN" action="GOOD" type="JUMPER" paint="Y" vscore="26" hscore="29"></play>
      <play vh="V" time="01:42" uni="32" team="COR" checkname="MILLER,SHONN" action="GOOD" type="LAYUP" paint="Y" vscore="28" hscore="29"></play>
      <play vh="H" time="01:42" uni="14" team="MASON" checkname="THOMPSON,SHEVON" action="FOUL"></play>
      <play vh="V" time="01:42" uni="32" team="COR" checkname="MILLER,SHONN" action="GOOD" type="FT" vscore="29" hscore="29"></play>
      <play vh="V" time="01:42" uni="04" team="COR" checkname="LAMORE,DAVE" action="SUB" type="IN"></play>
      <play vh="V" time="01:42" uni="00" team="COR" checkname="ONUORAH,DAVID" action="SUB" type="OUT"></play>
      <play vh="H" time="01:10" uni="25" team="MASON" checkname="ROYAL,JULIAN" action="GOOD" type="JUMPER" vscore="29" hscore="31"></play>
      <play vh="H" time="01:10" uni="22" team="MASON" checkname="MOORE,MARQUISE" action="ASSIST"></play>
      <play vh="V" time="00:57" uni="32" team="COR" checkname="MILLER,SHONN" action="GOOD" type="3PTR" vscore="32" hscore="31"></play>
      <play vh="V" time="00:57" uni="13" team="COR" checkname="CHERRY,DEVIN" action="ASSIST"></play>
      <play vh="H" time="00:30" uni="14" team="MASON" checkname="THOMPSON,SHEVON" action="MISS" type="LAYUP"></play>
      <play vh="V" time="00:30" uni="32" team="COR" checkname="MILLER,SHONN" action="REBOUND" type="DEF"></play>
      <play vh="V" time="00:03" uni="32" team="COR" checkname="MILLER,SHONN" action="GOOD" type="JUMPER" vscore="34" hscore="31"></play>
      <clock time="00:00"></clock>
    </period>
    <period number="2" time="20:00">
      <special vh="V" pts_to="2" pts_ch2="2" pts_paint="14" pts_fastb="4" pts_bench="3" ties="0" leads="0"
               poss_count="46" poss_time="661" score_count="10" score_time="272" large_lead="15" large_lead_t="2nd-01:30"></special>
      <special vh="H" pts_to="7" pts_ch2="5" pts_paint="6" pts_fastb="0" pts_bench="7" ties="0" leads="0"
               poss_count="45" poss_time="537" score_count="11" score_time="155" large_lead="3" large_lead_t="1st-02:04"></special>
      <summary vh="V" fgm="11" fga="25" fgm3="3" fga3="10" ftm="9" fta="14" blk="1" stl="0" ast="3"
               oreb="4" dreb="21" treb="25" pf="11" tf="0" to="8"></summary>
      <summary vh="H" fgm="10" fga="35" fgm3="3" fga3="16" ftm="6" fta="14" blk="3" stl="4" ast="4"
               oreb="8" dreb="11" treb="19" pf="13" tf="0" to="2"></summary>
      <play vh="V" time="19:53" uni="32" team="COR" checkname="MILLER,SHONN" action="GOOD" type="3PTR" vscore="37" hscore="31"></play>
      <play vh="V" time="19:53" uni="13" team="COR" checkname="CHERRY,DEVIN" action="ASSIST"></play>
      <play vh="H" time="19:13" uni="03" team="MASON" checkname="HOLLOWAY,PATRICK" action="FOUL"></play>
      <play vh="H" time="19:13" uni="03" team="MASON" checkname="HOLLOWAY,PATRICK" action="TURNOVER"></play>
      <play vh="H" time="19:13" uni="04" team="MASON" checkname="COPES,ERIK" action="SUB" type="IN"></play>
      <play vh="H" time="19:13" uni="13" team="MASON" checkname="EDWARDS,COREY" action="SUB" type="IN"></play>
      <play vh="H" time="19:13" uni="03" team="MASON" checkname="HOLLOWAY,PATRICK" action="SUB" type="OUT"></play>
      <play vh="H" time="19:13" uni="14" team="MASON" checkname="THOMPSON,SHEVON" action="SUB" type="OUT"></play>
      <play vh="V" time="18:54" uni="00" team="COR" checkname="ONUORAH,DAVID" action="GOOD" type="DUNK" paint="Y" vscore="39" hscore="31"></play>
      <play vh="H" time="18:36" uni="10" team="MASON" checkname="GUJANICIC,MARKO" action="MISS" type="3PTR"></play>
      <play vh="V" time="18:36" uni="00" team="COR" checkname="ONUORAH,DAVID" action="REBOUND" type="DEF"></play>
      <play vh="V" time="18:06" uni="05" team="COR" checkname="HATTER,ROBERT" action="TURNOVER"></play>
      <play vh="H" time="18:06" uni="31" team="MASON" checkname="JENKINS,JALEN" action="STEAL"></play>
      <play vh="H" time="18:06" uni="01" team="MASON" checkname="GRAY,VAUGHN" action="SUB" type="IN"></play>
      <play vh="H" time="18:06" uni="10" team="MASON" checkname="GUJANICIC,MARKO" action="SUB" type="OUT"></play>
      <play vh="H" time="17:38" uni="13" team="MASON" checkname="EDWARDS,COREY" action="MISS" type="3PTR"></play>
      <play vh="V" time="17:38" uni="13" team="COR" checkname="CHERRY,DEVIN" action="REBOUND" type="DEF"></play>
      <play vh="V" time="17:33" uni="13" team="COR" checkname="CHERRY,DEVIN" action="GOOD" type="LAYUP" paint="Y" fastb="Y" vscore="41" hscore="31"></play>
      <play vh="H" time="17:31" uni="TM" team="MASON" checkname="TEAM" action="TIMEOUT" type="30SEC"></play>
      <play vh="H" time="16:57" uni="13" team="MASON" checkname="EDWARDS,COREY" action="MISS" type="LAYUP"></play>
      <play vh="V" time="16:57" uni="32" team="COR" checkname="MILLER,SHONN" action="BLOCK"></play>
      <play vh="H" time="16:57" uni="TM" team="MASON" checkname="TEAM" action="REBOUND" type="OFF"></play>
      <play vh="H" time="16:57" uni="03" team="MASON" checkname="HOLLOWAY,PATRICK" action="SUB" type="IN"></play>
      <play vh="H" time="16:57" uni="22" team="MASON" checkname="MOORE,MARQUISE" action="SUB" type="OUT"></play>
      <play vh="H" time="16:54" uni="03" team="MASON" checkname="HOLLOWAY,PATRICK" action="MISS" type="3PTR"></play>
      <play vh="V" time="16:54" uni="13" team="COR" checkname="CHERRY,DEVIN" action="REBOUND" type="DEF"></play>
      <play vh="V" time="16:44" uni="13" team="COR" checkname="CHERRY,DEVIN" action="TURNOVER"></play>
      <play vh="H" time="16:44" uni="01" team="MASON" checkname="GRAY,VAUGHN" action="STEAL"></play>
      <play vh="V" time="16:44" uni="05" team="COR" checkname="HATTER,ROBERT" action="FOUL"></play>
      <play vh="H" time="16:34" uni="03" team="MASON" checkname="HOLLOWAY,PATRICK" action="MISS" type="LAYUP"></play>
      <play vh="H" time="16:34" uni="04" team="MASON" checkname="COPES,ERIK" action="REBOUND" type="OFF"></play>
      <play vh="V" time="16:33" uni="00" team="COR" checkname="ONUORAH,DAVID" action="FOUL"></play>
      <play vh="H" time="16:33" uni="04" team="MASON" checkname="COPES,ERIK" action="GOOD" type="FT" vscore="41" hscore="32"></play>
      <play vh="H" time="16:33" uni="04" team="MASON" checkname="COPES,ERIK" action="MISS" type="FT"></play>
      <play vh="H" time="16:33" uni="TM" team="MASON" checkname="TEAM" action="REBOUND" type="OFF"></play>
      <play vh="H" time="16:22" uni="04" team="MASON" checkname="COPES,ERIK" action="MISS" type="JUMPER"></play>
      <play vh="V" time="16:22" uni="TM" team="COR" checkname="TEAM" action="REBOUND" type="DEADB"></play>
      <play vh="V" time="16:11" uni="13" team="COR" checkname="CHERRY,DEVIN" action="MISS" type="3PTR"></play>
      <play vh="V" time="16:11" uni="23" team="COR" checkname="CANCER,GALAL" action="REBOUND" type="OFF"></play>
      <play vh="V" time="16:06" uni="23" team="COR" checkname="CANCER,GALAL" action="MISS" type="LAYUP"></play>
      <play vh="H" time="16:06" uni="04" team="MASON" checkname="COPES,ERIK" action="BLOCK"></play>
      <play vh="H" time="16:04" uni="31" team="MASON" checkname="JENKINS,JALEN" action="REBOUND" type="DEF"></play>
      <play vh="H" time="15:54" uni="01" team="MASON" checkname="GRAY,VAUGHN" action="MISS" type="3PTR"></play>
      <play vh="H" time="15:54" uni="31" team="MASON" checkname="JENKINS,JALEN" action="REBOUND" type="OFF"></play>
      <play vh="H" time="15:48" uni="01" team="MASON" checkname="GRAY,VAUGHN" action="MISS" type="3PTR"></play>
      <play vh="V" time="15:48" uni="00" team="COR" checkname="ONUORAH,DAVID" action="REBOUND" type="DEF"></play>
      <play vh="V" time="15:24" uni="05" team="COR" checkname="HATTER,ROBERT" action="GOOD" type="LAYUP" paint="Y" vscore="43" hscore="32"></play>
      <play vh="H" time="14:59" uni="03" team="MASON" checkname="HOLLOWAY,PATRICK" action="GOOD" type="JUMPER" vscore="43" hscore="34"></play>
      <play vh="H" time="14:58" uni="TM" team="MASON" checkname="TEAM" action="TIMEOUT" type="30SEC"></play>
      <play vh="H" time="14:58" uni="44" team="MASON" checkname="JACKSON,ISAIAH" action="SUB" type="IN"></play>
      <play vh="H" time="14:58" uni="01" team="MASON" checkname="GRAY,VAUGHN" action="SUB" type="OUT"></play>
      <play vh="V" time="14:46" uni="32" team="COR" checkname="MILLER,SHONN" action="MISS" type="JUMPER"></play>
      <play vh="H" time="14:46" uni="44" team="MASON" checkname="JACKSON,ISAIAH" action="REBOUND" type="DEF"></play>
      <play vh="V" time="14:28" uni="TM" team="COR" checkname="TEAM" action="TIMEOUT" type="MEDIA"></play>
      <play vh="V" time="14:28" uni="50" team="COR" checkname="GIDDENS,DEION" action="SUB" type="IN"></play>
      <play vh="V" time="14:28" uni="00" team="COR" checkname="ONUORAH,DAVID" action="SUB" type="OUT"></play>
      <play vh="H" time="14:28" uni="22" team="MASON" checkname="MOORE,MARQUISE" action="SUB" type="IN"></play>
      <play vh="H" time="14:28" uni="13" team="MASON" checkname="EDWARDS,COREY" action="SUB" type="OUT"></play>
      <play vh="H" time="14:27" uni="31" team="MASON" checkname="JENKINS,JALEN" action="FOUL"></play>
      <play vh="H" time="14:27" uni="31" team="MASON" checkname="JENKINS,JALEN" action="TURNOVER"></play>
      <play vh="V" time="14:27" uni="01" team="COR" checkname="SMITH,DARRYL" action="SUB" type="IN"></play>
      <play vh="V" time="14:27" uni="05" team="COR" checkname="HATTER,ROBERT" action="SUB" type="OUT"></play>
      <play vh="V" time="14:00" uni="23" team="COR" checkname="CANCER,GALAL" action="MISS" type="3PTR"></play>
      <play vh="H" time="14:00" uni="44" team="MASON" checkname="JACKSON,ISAIAH" action="REBOUND" type="DEF"></play>
      <play vh="V" time="13:46" uni="32" team="COR" checkname="MILLER,SHONN" action="FOUL"></play>
      <play vh="H" time="13:46" uni="31" team="MASON" checkname="JENKINS,JALEN" action="MISS" type="FT"></play>
      <play vh="H" time="13:46" uni="TM" team="MASON" checkname="TEAM" action="REBOUND" type="DEADB"></play>
      <play vh="H" time="13:46" uni="31" team="MASON" checkname="JENKINS,JALEN" action="MISS" type="FT"></play>
      <play vh="V" time="13:46" uni="32" team="COR" checkname="MILLER,SHONN" action="REBOUND" type="DEF"></play>
      <play vh="V" time="13:40" uni="13" team="COR" checkname="CHERRY,DEVIN" action="TURNOVER"></play>
      <play vh="H" time="13:21" uni="44" team="MASON" checkname="JACKSON,ISAIAH" action="MISS" type="3PTR"></play>
      <play vh="V" time="13:21" uni="32" team="COR" checkname="MILLER,SHONN" action="REBOUND" type="DEF"></play>
      <play vh="H" time="13:21" uni="31" team="MASON" checkname="JENKINS,JALEN" action="FOUL"></play>
      <play vh="H" time="13:21" uni="25" team="MASON" checkname="ROYAL,JULIAN" action="SUB" type="IN"></play>
      <play vh="H" time="13:21" uni="31" team="MASON" checkname="JENKINS,JALEN" action="SUB" type="OUT"></play>
      <play vh="V" time="13:05" uni="13" team="COR" checkname="CHERRY,DEVIN" action="GOOD" type="LAYUP" paint="Y" vscore="45" hscore="34"></play>
      <play vh="H" time="12:47" uni="44" team="MASON" checkname="JACKSON,ISAIAH" action="MISS" type="JUMPER"></play>
      <play vh="H" time="12:47" uni="22" team="MASON" checkname="MOORE,MARQUISE" action="REBOUND" type="OFF"></play>
      <play vh="H" time="12:43" uni="22" team="MASON" checkname="MOORE,MARQUISE" action="GOOD" type="JUMPER" vscore="45" hscore="36"></play>
      <play vh="V" time="12:18" uni="13" team="COR" checkname="CHERRY,DEVIN" action="MISS" type="LAYUP"></play>
      <play vh="H" time="12:18" uni="04" team="MASON" checkname="COPES,ERIK" action="BLOCK"></play>
      <play vh="H" time="12:17" uni="04" team="MASON" checkname="COPES,ERIK" action="REBOUND" type="DEF"></play>
      <play vh="H" time="12:10" uni="44" team="MASON" checkname="JACKSON,ISAIAH" action="GOOD" type="3PTR" vscore="45" hscore="39"></play>
      <play vh="H" time="12:10" uni="22" team="MASON" checkname="MOORE,MARQUISE" action="ASSIST"></play>
      <play vh="V" time="11:49" uni="01" team="COR" checkname="SMITH,DARRYL" action="GOOD" type="3PTR" vscore="48" hscore="39"></play>
      <play vh="V" time="11:49" uni="23" team="COR" checkname="CANCER,GALAL" action="ASSIST"></play>
      <play vh="H" time="11:35" uni="03" team="MASON" checkname="HOLLOWAY,PATRICK" action="MISS" type="3PTR"></play>
      <play vh="V" time="11:35" uni="32" team="COR" checkname="MILLER,SHONN" action="REBOUND" type="DEF"></play>
      <play vh="V" time="11:27" uni="23" team="COR" checkname="CANCER,GALAL" action="MISS" type="3PTR"></play>
      <play vh="H" time="11:27" uni="22" team="MASON" checkname="MOORE,MARQUISE" action="REBOUND" type="DEF"></play>
      <play vh="V" time="11:05" uni="50" team="COR" checkname="GIDDENS,DEION" action="FOUL"></play>
      <play vh="H" time="11:05" uni="TM" team="MASON" checkname="TEAM" action="TIMEOUT" type="MEDIA"></play>
      <play vh="H" time="11:02" uni="25" team="MASON" checkname="ROYAL,JULIAN" action="MISS" type="FT"></play>
      <play vh="H" time="11:02" uni="TM" team="MASON" checkname="TEAM" action="REBOUND" type="DEADB"></play>
      <play vh="H" time="11:02" uni="25" team="MASON" checkname="ROYAL,JULIAN" action="GOOD" type="FT" vscore="48" hscore="40"></play>
      <play vh="V" time="11:02" uni="05" team="COR" checkname="HATTER,ROBERT" action="GOOD" type="3PTR" vscore="51" hscore="40"></play>
      <play vh="H" time="11:02" uni="25" team="MASON" checkname="ROYAL,JULIAN" action="MISS" type="3PTR"></play>
      <play vh="V" time="11:02" uni="50" team="COR" checkname="GIDDENS,DEION" action="REBOUND" type="DEF"></play>
      <play vh="V" time="11:02" uni="50" team="COR" checkname="GIDDENS,DEION" action="MISS" type="JUMPER"></play>
      <play vh="H" time="11:02" uni="25" team="MASON" checkname="ROYAL,JULIAN" action="REBOUND" type="DEF"></play>
      <play vh="H" time="11:02" uni="44" team="MASON" checkname="JACKSON,ISAIAH" action="MISS" type="3PTR"></play>
      <play vh="V" time="11:02" uni="TM" team="COR" checkname="TEAM" action="REBOUND" type="DEF"></play>
      <play vh="V" time="11:02" uni="05" team="COR" checkname="HATTER,ROBERT" action="SUB" type="IN"></play>
      <play vh="V" time="11:02" uni="13" team="COR" checkname="CHERRY,DEVIN" action="SUB" type="OUT"></play>
      <play vh="H" time="11:02" uni="14" team="MASON" checkname="THOMPSON,SHEVON" action="SUB" type="IN"></play>
      <play vh="H" time="11:02" uni="13" team="MASON" checkname="EDWARDS,COREY" action="SUB" type="IN"></play>
      <play vh="H" time="11:02" uni="04" team="MASON" checkname="COPES,ERIK" action="SUB" type="OUT"></play>
      <play vh="H" time="11:02" uni="03" team="MASON" checkname="HOLLOWAY,PATRICK" action="SUB" type="OUT"></play>
      <play vh="V" time="10:51" uni="00" team="COR" checkname="ONUORAH,DAVID" action="SUB" type="IN"></play>
      <play vh="V" time="10:51" uni="04" team="COR" checkname="LAMORE,DAVE" action="SUB" type="IN"></play>
      <play vh="V" time="10:51" uni="13" team="COR" checkname="CHERRY,DEVIN" action="SUB" type="IN"></play>
      <play vh="V" time="10:51" uni="23" team="COR" checkname="CANCER,GALAL" action="SUB" type="OUT"></play>
      <play vh="V" time="10:51" uni="32" team="COR" checkname="MILLER,SHONN" action="SUB" type="OUT"></play>
      <play vh="V" time="10:51" uni="50" team="COR" checkname="GIDDENS,DEION" action="SUB" type="OUT"></play>
      <play vh="H" time="10:51" uni="03" team="MASON" checkname="HOLLOWAY,PATRICK" action="SUB" type="IN"></play>
      <play vh="H" time="10:51" uni="44" team="MASON" checkname="JACKSON,ISAIAH" action="SUB" type="OUT"></play>
      <play vh="V" time="09:12" uni="05" team="COR" checkname="HATTER,ROBERT" action="MISS" type="3PTR"></play>
      <play vh="V" time="09:12" uni="05" team="COR" checkname="HATTER,ROBERT" action="REBOUND" type="OFF"></play>
      <play vh="V" time="08:50" uni="05" team="COR" checkname="HATTER,ROBERT" action="MISS" type="3PTR"></play>
      <play vh="V" time="08:50" uni="TM" team="COR" checkname="TEAM" action="REBOUND" type="OFF"></play>
      <play vh="V" time="08:43" uni="00" team="COR" checkname="ONUORAH,DAVID" action="GOOD" type="JUMPER" paint="Y" vscore="53" hscore="40"></play>
      <play vh="H" time="08:17" uni="03" team="MASON" checkname="HOLLOWAY,PATRICK" action="MISS" type="JUMPER"></play>
      <play vh="V" time="08:17" uni="05" team="COR" checkname="HATTER,ROBERT" action="REBOUND" type="DEF"></play>
      <play vh="H" time="08:08" uni="13" team="MASON" checkname="EDWARDS,COREY" action="FOUL"></play>
      <play vh="H" time="08:08" uni="31" team="MASON" checkname="JENKINS,JALEN" action="SUB" type="IN"></play>
      <play vh="H" time="08:08" uni="25" team="MASON" checkname="ROYAL,JULIAN" action="SUB" type="OUT"></play>
      <play vh="V" time="07:55" uni="05" team="COR" checkname="HATTER,ROBERT" action="MISS" type="LAYUP"></play>
      <play vh="H" time="07:55" uni="TM" team="MASON" checkname="TEAM" action="REBOUND" type="DEADB"></play>
      <play vh="H" time="07:55" uni="TM" team="MASON" checkname="TEAM" action="TIMEOUT" type="MEDIA"></play>
      <play vh="H" time="07:32" uni="03" team="MASON" checkname="HOLLOWAY,PATRICK" action="MISS" type="3PTR"></play>
      <play vh="V" time="07:32" uni="00" team="COR" checkname="ONUORAH,DAVID" action="REBOUND" type="DEF"></play>
      <play vh="V" time="07:07" uni="13" team="COR" checkname="CHERRY,DEVIN" action="MISS" type="JUMPER"></play>
      <play vh="H" time="07:07" uni="03" team="MASON" checkname="HOLLOWAY,PATRICK" action="REBOUND" type="DEF"></play>
      <play vh="V" time="07:05" uni="13" team="COR" checkname="CHERRY,DEVIN" action="FOUL"></play>
      <play vh="V" time="07:05" uni="32" team="COR" checkname="MILLER,SHONN" action="SUB" type="IN"></play>
      <play vh="V" time="07:05" uni="04" team="COR" checkname="LAMORE,DAVE" action="SUB" type="OUT"></play>
      <play vh="H" time="07:05" uni="04" team="MASON" checkname="COPES,ERIK" action="SUB" type="IN"></play>
      <play vh="H" time="07:05" uni="14" team="MASON" checkname="THOMPSON,SHEVON" action="SUB" type="OUT"></play>
      <play vh="H" time="06:49" uni="31" team="MASON" checkname="JENKINS,JALEN" action="GOOD" type="JUMPER" paint="Y" vscore="53" hscore="42"></play>
      <play vh="V" time="06:23" uni="13" team="COR" checkname="CHERRY,DEVIN" action="TURNOVER"></play>
      <play vh="H" time="06:06" uni="31" team="MASON" checkname="JENKINS,JALEN" action="MISS" type="JUMPER"></play>
      <play vh="V" time="06:06" uni="32" team="COR" checkname="MILLER,SHONN" action="REBOUND" type="DEF"></play>
      <play vh="V" time="05:55" uni="32" team="COR" checkname="MILLER,SHONN" action="MISS" type="JUMPER"></play>
      <play vh="H" time="05:55" uni="13" team="MASON" checkname="EDWARDS,COREY" action="BLOCK"></play>
      <play vh="V" time="05:55" uni="TM" team="COR" checkname="TEAM" action="REBOUND" type="OFF"></play>
      <play vh="H" time="05:55" uni="14" team="MASON" checkname="THOMPSON,SHEVON" action="SUB" type="IN"></play>
      <play vh="H" time="05:55" uni="04" team="MASON" checkname="COPES,ERIK" action="SUB" type="OUT"></play>
      <play vh="V" time="05:41" uni="13" team="COR" checkname="CHERRY,DEVIN" action="MISS" type="3PTR"></play>
      <play vh="H" time="05:41" uni="14" team="MASON" checkname="THOMPSON,SHEVON" action="REBOUND" type="DEF"></play>
      <play vh="H" time="05:21" uni="14" team="MASON" checkname="THOMPSON,SHEVON" action="MISS" type="LAYUP"></play>
      <play vh="V" time="05:21" uni="00" team="COR" checkname="ONUORAH,DAVID" action="REBOUND" type="DEF"></play>
      <play vh="V" time="04:46" uni="32" team="COR" checkname="MILLER,SHONN" action="MISS" type="3PTR"></play>
      <play vh="H" time="04:46" uni="14" team="MASON" checkname="THOMPSON,SHEVON" action="REBOUND" type="DEF"></play>
      <play vh="H" time="04:28" uni="13" team="MASON" checkname="EDWARDS,COREY" action="MISS" type="LAYUP"></play>
      <play vh="H" time="04:28" uni="31" team="MASON" checkname="JENKINS,JALEN" action="REBOUND" type="OFF"></play>
      <play vh="H" time="04:22" uni="31" team="MASON" checkname="JENKINS,JALEN" action="MISS" type="JUMPER"></play>
      <play vh="V" time="04:22" uni="32" team="COR" checkname="MILLER,SHONN" action="REBOUND" type="DEF"></play>
      <play vh="V" time="04:16" uni="05" team="COR" checkname="HATTER,ROBERT" action="GOOD" type="LAYUP" paint="Y" fastb="Y" vscore="55" hscore="42"></play>
      <play vh="V" time="04:16" uni="13" team="COR" checkname="CHERRY,DEVIN" action="ASSIST"></play>
      <play vh="H" time="03:55" uni="03" team="MASON" checkname="HOLLOWAY,PATRICK" action="MISS" type="3PTR"></play>
      <play vh="V" time="03:55" uni="32" team="COR" checkname="MILLER,SHONN" action="REBOUND" type="DEF"></play>
      <play vh="V" time="03:41" uni="32" team="COR" checkname="MILLER,SHONN" action="FOUL"></play>
      <play vh="V" time="03:41" uni="32" team="COR" checkname="MILLER,SHONN" action="TURNOVER"></play>
      <play vh="H" time="03:41" uni="TM" team="MASON" checkname="TEAM" action="TIMEOUT" type="MEDIA"></play>
      <play vh="V" time="03:41" uni="23" team="COR" checkname="CANCER,GALAL" action="SUB" type="IN"></play>
      <play vh="V" time="03:41" uni="01" team="COR" checkname="SMITH,DARRYL" action="SUB" type="OUT"></play>
      <play vh="H" time="03:41" uni="44" team="MASON" checkname="JACKSON,ISAIAH" action="SUB" type="IN"></play>
      <play vh="H" time="03:41" uni="13" team="MASON" checkname="EDWARDS,COREY" action="SUB" type="OUT"></play>
      <play vh="H" time="03:12" uni="31" team="MASON" checkname="JENKINS,JALEN" action="GOOD" type="LAYUP" paint="Y" vscore="55" hscore="44"></play>
      <play vh="V" time="02:37" uni="32" team="COR" checkname="MILLER,SHONN" action="GOOD" type="JUMPER" vscore="57" hscore="44"></play>
      <play vh="H" time="02:19" uni="03" team="MASON" checkname="HOLLOWAY,PATRICK" action="GOOD" type="JUMPER" vscore="57" hscore="46"></play>
      <play vh="H" time="02:19" uni="44" team="MASON" checkname="JACKSON,ISAIAH" action="ASSIST"></play>
      <play vh="H" time="02:19" uni="01" team="MASON" checkname="GRAY,VAUGHN" action="SUB" type="IN"></play>
      <play vh="H" time="02:19" uni="03" team="MASON" checkname="HOLLOWAY,PATRICK" action="SUB" type="OUT"></play>
      <play vh="H" time="02:17" uni="13" team="MASON" checkname="EDWARDS,COREY" action="SUB" type="IN"></play>
      <play vh="H" time="02:17" uni="44" team="MASON" checkname="JACKSON,ISAIAH" action="SUB" type="OUT"></play>
      <play vh="H" time="02:11" uni="22" team="MASON" checkname="MOORE,MARQUISE" action="FOUL"></play>
      <play vh="H" time="02:11" uni="03" team="MASON" checkname="HOLLOWAY,PATRICK" action="SUB" type="IN"></play>
      <play vh="H" time="02:11" uni="01" team="MASON" checkname="GRAY,VAUGHN" action="SUB" type="OUT"></play>
      <play vh="H" time="02:09" uni="22" team="MASON" checkname="MOORE,MARQUISE" action="FOUL"></play>
      <play vh="H" time="02:09" uni="44" team="MASON" checkname="JACKSON,ISAIAH" action="SUB" type="IN"></play>
      <play vh="H" time="02:09" uni="22" team="MASON" checkname="MOORE,MARQUISE" action="SUB" type="OUT"></play>
      <play vh="H" time="02:05" uni="44" team="MASON" checkname="JACKSON,ISAIAH" action="FOUL"></play>
      <play vh="V" time="02:05" uni="13" team="COR" checkname="CHERRY,DEVIN" action="GOOD" type="FT" vscore="58" hscore="46"></play>
      <play vh="V" time="02:05" uni="13" team="COR" checkname="CHERRY,DEVIN" action="MISS" type="FT"></play>
      <play vh="H" time="02:05" uni="14" team="MASON" checkname="THOMPSON,SHEVON" action="REBOUND" type="DEF"></play>
      <play vh="H" time="02:05" uni="22" team="MASON" checkname="MOORE,MARQUISE" action="SUB" type="IN"></play>
      <play vh="H" time="02:05" uni="13" team="MASON" checkname="EDWARDS,COREY" action="SUB" type="OUT"></play>
      <play vh="V" time="02:04" uni="00" team="COR" checkname="ONUORAH,DAVID" action="FOUL"></play>
      <play vh="H" time="02:04" uni="14" team="MASON" checkname="THOMPSON,SHEVON" action="GOOD" type="FT" vscore="58" hscore="47"></play>
      <play vh="H" time="02:04" uni="14" team="MASON" checkname="THOMPSON,SHEVON" action="MISS" type="FT"></play>
      <play vh="V" time="02:04" uni="13" team="COR" checkname="CHERRY,DEVIN" action="REBOUND" type="DEF"></play>
      <play vh="H" time="02:04" uni="13" team="MASON" checkname="EDWARDS,COREY" action="SUB" type="IN"></play>
      <play vh="H" time="02:04" uni="22" team="MASON" checkname="MOORE,MARQUISE" action="SUB" type="OUT"></play>
      <play vh="H" time="01:59" uni="44" team="MASON" checkname="JACKSON,ISAIAH" action="FOUL"></play>
      <play vh="V" time="01:59" uni="13" team="COR" checkname="CHERRY,DEVIN" action="GOOD" type="FT" vscore="59" hscore="47"></play>
      <play vh="V" time="01:59" uni="13" team="COR" checkname="CHERRY,DEVIN" action="GOOD" type="FT" vscore="60" hscore="47"></play>
      <play vh="H" time="01:59" uni="22" team="MASON" checkname="MOORE,MARQUISE" action="SUB" type="IN"></play>
      <play vh="H" time="01:59" uni="13" team="MASON" checkname="EDWARDS,COREY" action="SUB" type="OUT"></play>
      <play vh="H" time="01:49" uni="44" team="MASON" checkname="JACKSON,ISAIAH" action="MISS" type="LAYUP"></play>
      <play vh="V" time="01:49" uni="32" team="COR" checkname="MILLER,SHONN" action="REBOUND" type="DEF"></play>
      <play vh="V" time="01:43" uni="13" team="COR" checkname="CHERRY,DEVIN" action="TURNOVER"></play>
      <play vh="H" time="01:43" uni="22" team="MASON" checkname="MOORE,MARQUISE" action="STEAL"></play>
      <play vh="H" time="01:33" uni="31" team="MASON" checkname="JENKINS,JALEN" action="MISS" type="JUMPER"></play>
      <play vh="V" time="01:33" uni="05" team="COR" checkname="HATTER,ROBERT" action="REBOUND" type="DEF"></play>
      <play vh="H" time="01:30" uni="03" team="MASON" checkname="HOLLOWAY,PATRICK" action="FOUL"></play>
      <play vh="V" time="01:30" uni="05" team="COR" checkname="HATTER,ROBERT" action="GOOD" type="FT" vscore="61" hscore="47"></play>
      <play vh="V" time="01:30" uni="05" team="COR" checkname="HATTER,ROBERT" action="GOOD" type="FT" vscore="62" hscore="47"></play>
      <play vh="V" time="01:24" uni="32" team="COR" checkname="MILLER,SHONN" action="FOUL"></play>
      <play vh="H" time="01:24" uni="03" team="MASON" checkname="HOLLOWAY,PATRICK" action="GOOD" type="FT" vscore="62" hscore="48"></play>
      <play vh="H" time="01:24" uni="03" team="MASON" checkname="HOLLOWAY,PATRICK" action="GOOD" type="FT" vscore="62" hscore="49"></play>
      <play vh="V" time="01:24" uni="01" team="COR" checkname="SMITH,DARRYL" action="SUB" type="IN"></play>
      <play vh="V" time="01:24" uni="00" team="COR" checkname="ONUORAH,DAVID" action="SUB" type="OUT"></play>
      <play vh="H" time="01:24" uni="13" team="MASON" checkname="EDWARDS,COREY" action="SUB" type="IN"></play>
      <play vh="H" time="01:24" uni="22" team="MASON" checkname="MOORE,MARQUISE" action="SUB" type="OUT"></play>
      <play vh="V" time="01:16" uni="13" team="COR" checkname="CHERRY,DEVIN" action="FOUL"></play>
      <play vh="V" time="01:16" uni="13" team="COR" checkname="CHERRY,DEVIN" action="TURNOVER"></play>
      <play vh="V" time="01:16" uni="00" team="COR" checkname="ONUORAH,DAVID" action="SUB" type="IN"></play>
      <play vh="V" time="01:16" uni="01" team="COR" checkname="SMITH,DARRYL" action="SUB" type="OUT"></play>
      <play vh="H" time="01:16" uni="22" team="MASON" checkname="MOORE,MARQUISE" action="SUB" type="IN"></play>
      <play vh="H" time="01:16" uni="13" team="MASON" checkname="EDWARDS,COREY" action="SUB" type="OUT"></play>
      <play vh="V" time="01:12" uni="05" team="COR" checkname="HATTER,ROBERT" action="FOUL"></play>
      <play vh="H" time="01:12" uni="22" team="MASON" checkname="MOORE,MARQUISE" action="GOOD" type="FT" vscore="62" hscore="50"></play>
      <play vh="H" time="01:12" uni="22" team="MASON" checkname="MOORE,MARQUISE" action="MISS" type="FT"></play>
      <play vh="V" time="01:12" uni="13" team="COR" checkname="CHERRY,DEVIN" action="REBOUND" type="DEF"></play>
      <play vh="H" time="01:10" uni="10" team="MASON" checkname="GUJANICIC,MARKO" action="FOUL"></play>
      <play vh="V" time="01:09" uni="13" team="COR" checkname="CHERRY,DEVIN" action="MISS" type="FT"></play>
      <play vh="V" time="01:09" uni="TM" team="COR" checkname="TEAM" action="REBOUND" type="DEADB"></play>
      <play vh="V" time="01:09" uni="13" team="COR" checkname="CHERRY,DEVIN" action="GOOD" type="FT" vscore="63" hscore="50"></play>
      <play vh="H" time="01:02" uni="03" team="MASON" checkname="HOLLOWAY,PATRICK" action="MISS" type="3PTR"></play>
      <play vh="H" time="01:02" uni="44" team="MASON" checkname="JACKSON,ISAIAH" action="REBOUND" type="OFF"></play>
      <play vh="H" time="01:00" uni="44" team="MASON" checkname="JACKSON,ISAIAH" action="GOOD" type="JUMPER" vscore="63" hscore="52"></play>
      <play vh="H" time="00:59" uni="TM" team="MASON" checkname="TEAM" action="TIMEOUT" type="TEAM"></play>
      <play vh="V" time="00:59" uni="TM" team="COR" checkname="TEAM" action="TIMEOUT" type="30SEC"></play>
      <play vh="V" time="00:50" uni="05" team="COR" checkname="HATTER,ROBERT" action="GOOD" type="LAYUP" paint="Y" vscore="65" hscore="52"></play>
      <play vh="V" time="00:50" uni="TM" team="COR" checkname="TEAM" action="TIMEOUT" type="30SEC"></play>
      <play vh="V" time="00:42" uni="13" team="COR" checkname="CHERRY,DEVIN" action="FOUL"></play>
      <play vh="H" time="00:42" uni="03" team="MASON" checkname="HOLLOWAY,PATRICK" action="MISS" type="FT"></play>
      <play vh="H" time="00:42" uni="TM" team="MASON" checkname="TEAM" action="REBOUND" type="DEADB"></play>
      <play vh="H" time="00:42" uni="03" team="MASON" checkname="HOLLOWAY,PATRICK" action="MISS" type="FT"></play>
      <play vh="V" time="00:42" uni="32" team="COR" checkname="MILLER,SHONN" action="REBOUND" type="DEF"></play>
      <play vh="H" time="00:42" uni="01" team="MASON" checkname="GRAY,VAUGHN" action="SUB" type="IN"></play>
      <play vh="H" time="00:42" uni="14" team="MASON" checkname="THOMPSON,SHEVON" action="SUB" type="OUT"></play>
      <play vh="H" time="00:39" uni="01" team="MASON" checkname="GRAY,VAUGHN" action="FOUL"></play>
      <play vh="V" time="00:39" uni="32" team="COR" checkname="MILLER,SHONN" action="GOOD" type="FT" vscore="66" hscore="52"></play>
      <play vh="V" time="00:39" uni="32" team="COR" checkname="MILLER,SHONN" action="GOOD" type="FT" vscore="67" hscore="52"></play>
      <play vh="H" time="00:39" uni="14" team="MASON" checkname="THOMPSON,SHEVON" action="SUB" type="IN"></play>
      <play vh="H" time="00:39" uni="01" team="MASON" checkname="GRAY,VAUGHN" action="SUB" type="OUT"></play>
      <play vh="H" time="00:34" uni="03" team="MASON" checkname="HOLLOWAY,PATRICK" action="GOOD" type="3PTR" vscore="67" hscore="55"></play>
      <play vh="H" time="00:33" uni="22" team="MASON" checkname="MOORE,MARQUISE" action="ASSIST"></play>
      <play vh="H" time="00:32" uni="22" team="MASON" checkname="MOORE,MARQUISE" action="FOUL"></play>
      <play vh="V" time="00:32" uni="13" team="COR" checkname="CHERRY,DEVIN" action="MISS" type="FT"></play>
      <play vh="V" time="00:32" uni="TM" team="COR" checkname="TEAM" action="REBOUND" type="DEADB"></play>
      <play vh="V" time="00:32" uni="13" team="COR" checkname="CHERRY,DEVIN" action="MISS" type="FT"></play>
      <play vh="H" time="00:32" uni="31" team="MASON" checkname="JENKINS,JALEN" action="REBOUND" type="DEF"></play>
      <play vh="H" time="00:23" uni="03" team="MASON" checkname="HOLLOWAY,PATRICK" action="GOOD" type="LAYUP" paint="Y" vscore="67" hscore="57"></play>
      <play vh="V" time="00:21" uni="13" team="COR" checkname="CHERRY,DEVIN" action="TURNOVER"></play>
      <play vh="H" time="00:20" uni="31" team="MASON" checkname="JENKINS,JALEN" action="STEAL"></play>
      <play vh="H" time="00:17" uni="03" team="MASON" checkname="HOLLOWAY,PATRICK" action="GOOD" type="3PTR" vscore="67" hscore="60"></play>
      <play vh="H" time="00:17" uni="22" team="MASON" checkname="MOORE,MARQUISE" action="ASSIST"></play>
      <play vh="H" time="00:17" uni="03" team="MASON" checkname="HOLLOWAY,PATRICK" action="FOUL"></play>
      <play vh="V" time="00:17" uni="13" team="COR" checkname="CHERRY,DEVIN" action="MISS" type="FT"></play>
      <play vh="V" time="00:17" uni="TM" team="COR" checkname="TEAM" action="REBOUND" type="DEADB"></play>
      <play vh="V" time="00:17" uni="13" team="COR" checkname="CHERRY,DEVIN" action="GOOD" type="FT" vscore="68" hscore="60"></play>
      <play vh="H" time="00:06" uni="22" team="MASON" checkname="MOORE,MARQUISE" action="MISS" type="3PTR"></play>
      <play vh="H" time="00:06" uni="14" team="MASON" checkname="THOMPSON,SHEVON" action="REBOUND" type="OFF"></play>
      <play vh="H" time="00:02" uni="14" team="MASON" checkname="THOMPSON,SHEVON" action="MISS" type="JUMPER"></play>
      <play vh="V" time="00:02" uni="23" team="COR" checkname="CANCER,GALAL" action="REBOUND" type="DEF"></play>
      <clock time="00:00"></clock>
    </period>
  </plays>
</bbgame>
